[{"time":0.0,"pose":{"rotation":{"radians":0.0},"translation":{"x":1.5,"y":3.0}},"velocity":0,"acceleration":3.0,"curvature":0,"holonomicRotation":0.0,"angularVelocity":0.0,"holonomicAngularVelocity":0.0},{"time":0.015298574133728636,"pose":{"rotation":{"radians":0.0},"translation":{"x":1.5003510695557878,"y":3.0}},"velocity":0.045895722401185904,"acceleration":2.9999999999999996,"curvature":0,"holonomicRotation":0.0,"angularVelocity":0.0,"holonomicAngularVelocity":0.0},{"time":0.02076256132992949,"pose":{"rotation":{"radians":0.0},"translation":{"x":1.5006466259294686,"y":3.0}},"velocity":0.062287683989788456,"acceleration":2.999999999999999,"curvature":0,"holonomicRotation":0.0,"angularVelocity":0.0,"holonomicAngularVelocity":0.0},{"time":0.024318884498347182,"pose":{"rotation":{"radians":0.0},"translation":{"x":1.500887112214866,"y":3.0}},"velocity":0.07295665349504153,"acceleration":2.999999999999999,"curvature":0,"holonomicRotation":0.0,"angularVelocity":0.0,"holonomicAngularVelocity":0.0},{"time":0.02674536104075416,"pose":{"rotation":{"radians":0.0},"translation":{"x":1.5010729715058004,"y":3.0}},"velocity":0.08023608312226246,"acceleration":3.0,"curvature":0,"holonomicRotation":0.0,"angularVelocity":0.0,"holonomicAngularVelocity":0.0},{"time":0.028338982528137442,"pose":{"rotation":{"radians":0.0},"translation":{"x":1.5012046468960951,"y":3.0}},"velocity":0.08501694758441232,"acceleration":3.0000000000000044,"curvature":0,"holonomicRotation":0.0,"angularVelocity":0.0,"holonomicAngularVelocity":0.0},{"time":0.029241311867187328,"pose":{"rotation":{"radians":0.0},"translation":{"x":1.5012825814795712,"y":3.0}},"velocity":0.08772393560156198,"acceleration":3.0000000000000075,"curvature":0,"holonomicRotation":0.0,"angularVelocity":0.0,"holonomicAngularVelocity":0.0},{"time":0.029520821466117123,"pose":{"rotation":{"radians":0.0},"translation":{"x":1.5013072183500515,"y":3.0}},"velocity":0.08856246439835137,"acceleration":3.0000000000000124,"curvature":0,"holonomicRotation":0.0,"angularVelocity":9912.93225806059,"holonomicAngularVelocity":0.0},{"time":0.02983774007019971,"pose":{"rotation":{"radians":3.141592653589793},"translation":{"x":1.5012790006013579,"y":3.0}},"velocity":0.08951322021059913,"acceleration":2.999999999999989,"curvature":0,"holonomicRotation":0.0,"angularVelocity":0.0,"holonomicAngularVelocity":0.0},{"time":0.030725292217663982,"pose":{"rotation":{"radians":3.141592653589793},"translation":{"x":1.5011983713273118,"y":3.0}},"velocity":0.09217587665299194,"acceleration":2.999999999999996,"curvature":0,"holonomicRotation":0.0,"angularVelocity":0.0,"holonomicAngularVelocity":0.0},{"time":0.03213163631445894,"pose":{"rotation":{"radians":3.141592653589793},"translation":{"x":1.501065773621736,"y":3.0}},"velocity":0.09639490894337684,"acceleration":3.0000000000000075,"curvature":0,"holonomicRotation":0.0,"angularVelocity":0.0,"holonomicAngularVelocity":0.0},{"time":0.0339880971483739,"pose":{"rotation":{"radians":3.141592653589793},"translation":{"x":1.5008816505784521,"y":3.0}},"velocity":0.1019642914451217,"acceleration":3.0,"curvature":0,"holonomicRotation":0.0,"angularVelocity":0.0,"holonomicAngularVelocity":0.0},{"time":0.036221461491042814,"pose":{"rotation":{"radians":3.141592653589793},"translation":{"x":1.5006464452912824,"y":3.0}},"velocity":0.10866438447312844,"acceleration":2.999999999999997,"curvature":0,"holonomicRotation":0.0,"angularVelocity":0.0,"holonomicAngularVelocity":0.0},{"time":0.03876283310985931,"pose":{"rotation":{"radians":3.141592653589793},"translation":{"x":1.5003606008540489,"y":3.0}},"velocity":0.11628849932957795,"acceleration":3.0000000000000053,"curvature":0,"holonomicRotation":0.0,"angularVelocity":0.0,"holonomicAngularVelocity":0.0},{"time":0.041552186781843255,"pose":{"rotation":{"radians":3.141592653589793},"translation":{"x":1.5000245603605733,"y":3.0}},"velocity":0.12465656034552977,"acceleration":2.9999999999999973,"curvature":0,"holonomicRotation":0.0,"angularVelocity":0.0,"holonomicAngularVelocity":0.0},{"time":0.04453964373023843,"pose":{"rotation":{"radians":3.141592653589793},"translation":{"x":1.4996387669046782,"y":3.0}},"velocity":0.1336189311907153,"acceleration":3.000000000000002,"curvature":0,"holonomicRotation":0.0,"angularVelocity":0.0,"holonomicAngularVelocity":0.0},{"time":0.04768489012896906,"pose":{"rotation":{"radians":3.141592653589793},"translation":{"x":1.4992036635801853,"y":3.0}},"velocity":0.1430546703869072,"acceleration":3.000000000000002,"curvature":0,"holonomicRotation":0.0,"angularVelocity":0.0,"holonomicAngularVelocity":0.0},{"time":0.05095581889693763,"pose":{"rotation":{"radians":3.141592653589793},"translation":{"x":1.4987196934809168,"y":3.0}},"velocity":0.1528674566908129,"acceleration":2.9999999999999956,"curvature":0,"holonomicRotation":0.0,"angularVelocity":0.0,"holonomicAngularVelocity":0.0},{"time":0.05432701598903113,"pose":{"rotation":{"radians":3.141592653589793},"translation":{"x":1.4981872997006944,"y":3.0}},"velocity":0.1629810479670934,"acceleration":3.000000000000002,"curvature":0,"holonomicRotation":0.0,"angularVelocity":0.0,"holonomicAngularVelocity":0.0},{"time":0.05777837754017486,"pose":{"rotation":{"radians":3.141592653589793},"translation":{"x":1.4976069253333406,"y":3.0}},"velocity":0.1733351326205246,"acceleration":3.000000000000002,"curvature":0,"holonomicRotation":0.0,"angularVelocity":0.0,"holonomicAngularVelocity":0.0},{"time":0.061293954173998126,"pose":{"rotation":{"radians":3.141592653589793},"translation":{"x":1.4969790134726768,"y":3.0}},"velocity":0.1838818625219944,"acceleration":3.0,"curvature":0,"holonomicRotation":0.0,"angularVelocity":0.0,"holonomicAngularVelocity":0.0},{"time":0.06486102829679825,"pose":{"rotation":{"radians":3.141592653589793},"translation":{"x":1.496304007212526,"y":3.0}},"velocity":0.1945830848903948,"acceleration":3.0000000000000058,"curvature":0,"holonomicRotation":0.0,"angularVelocity":0.0,"holonomicAngularVelocity":0.0},{"time":0.06846939488264692,"pose":{"rotation":{"radians":3.141592653589793},"translation":{"x":1.4955823496467093,"y":3.0}},"velocity":0.20540818464794078,"acceleration":2.999999999999996,"curvature":0,"holonomicRotation":0.0,"angularVelocity":0.0,"holonomicAngularVelocity":0.0},{"time":0.07211080747041886,"pose":{"rotation":{"radians":3.141592653589793},"translation":{"x":1.4948144838690494,"y":3.0}},"velocity":0.2163324224112566,"acceleration":3.000000000000004,"curvature":0,"holonomicRotation":0.0,"angularVelocity":0.0,"holonomicAngularVelocity":0.0},{"time":0.0757785533720245,"pose":{"rotation":{"radians":3.141592653589793},"translation":{"x":1.494000852973368,"y":3.0}},"velocity":0.2273356601160736,"acceleration":3.0000000000000075,"curvature":0,"holonomicRotation":0.0,"angularVelocity":0.0,"holonomicAngularVelocity":0.0},{"time":0.07946712799061827,"pose":{"rotation":{"radians":3.141592653589793},"translation":{"x":1.4931419000534871,"y":3.0}},"velocity":0.23840138397185487,"acceleration":3.0,"curvature":0,"holonomicRotation":0.0,"angularVelocity":0.0,"holonomicAngularVelocity":0.0},{"time":0.08317198445339659,"pose":{"rotation":{"radians":3.141592653589793},"translation":{"x":1.492238068203229,"y":3.0}},"velocity":0.24951595336018983,"acceleration":3.0,"curvature":0,"holonomicRotation":0.0,"angularVelocity":0.0,"holonomicAngularVelocity":0.0},{"time":0.08688934028862082,"pose":{"rotation":{"radians":3.141592653589793},"translation":{"x":1.4912898005164155,"y":3.0}},"velocity":0.26066802086586255,"acceleration":3.0000000000000075,"curvature":0,"holonomicRotation":0.0,"angularVelocity":0.0,"holonomicAngularVelocity":0.0},{"time":0.0906160273286284,"pose":{"rotation":{"radians":3.141592653589793},"translation":{"x":1.490297540086869,"y":3.0}},"velocity":0.2718480819858853,"acceleration":2.9999999999999925,"curvature":0,"holonomicRotation":0.0,"angularVelocity":0.0,"holonomicAngularVelocity":0.0},{"time":0.09434937446071412,"pose":{"rotation":{"radians":3.141592653589793},"translation":{"x":1.489261730008411,"y":3.0}},"velocity":0.28304812338214247,"acceleration":3.000000000000011,"curvature":0,"holonomicRotation":0.0,"angularVelocity":0.0,"holonomicAngularVelocity":0.0},{"time":0.09808711544757567,"pose":{"rotation":{"radians":3.141592653589793},"translation":{"x":1.488182813374864,"y":3.0}},"velocity":0.29426134634272716,"acceleration":3.0000000000000075,"curvature":0,"holonomicRotation":0.0,"angularVelocity":0.0,"holonomicAngularVelocity":0.0},{"time":0.10182731598169248,"pose":{"rotation":{"radians":3.141592653589793},"translation":{"x":1.48706123328005,"y":3.0}},"velocity":0.3054819479450776,"acceleration":3.0000000000000075,"curvature":0,"holonomicRotation":0.0,"angularVelocity":0.0,"holonomicAngularVelocity":0.0},{"time":0.10556831558225716,"pose":{"rotation":{"radians":3.141592653589793},"translation":{"x":1.4858974328177905,"y":3.0}},"velocity":0.31670494674677163,"acceleration":3.0,"curvature":0,"holonomicRotation":0.0,"angularVelocity":0.0,"holonomicAngularVelocity":0.0},{"time":0.10930868101602514,"pose":{"rotation":{"radians":3.141592653589793},"translation":{"x":1.4846918550819084,"y":3.0}},"velocity":0.3279260430480756,"acceleration":3.0,"curvature":0,"holonomicRotation":0.0,"angularVelocity":0.0,"holonomicAngularVelocity":0.0},{"time":0.11304716872137333,"pose":{"rotation":{"radians":3.141592653589793},"translation":{"x":1.483444943166225,"y":3.0}},"velocity":0.33914150616412014,"acceleration":3.0,"curvature":0,"holonomicRotation":0.0,"angularVelocity":0.0,"holonomicAngularVelocity":0.0},{"time":0.11678269431024461,"pose":{"rotation":{"radians":3.141592653589793},"translation":{"x":1.482157140164563,"y":3.0}},"velocity":0.35034808293073405,"acceleration":3.000000000000011,"curvature":0,"holonomicRotation":0.0,"angularVelocity":0.0,"holonomicAngularVelocity":0.0},{"time":0.12051430766886655,"pose":{"rotation":{"radians":3.141592653589793},"translation":{"x":1.4808288891707437,"y":3.0}},"velocity":0.36154292300659985,"acceleration":3.0,"curvature":0,"holonomicRotation":0.0,"angularVelocity":0.0,"holonomicAngularVelocity":0.0},{"time":0.12424117251408859,"pose":{"rotation":{"radians":3.141592653589793},"translation":{"x":1.4794606332785898,"y":3.0}},"velocity":0.372723517542266,"acceleration":3.000000000000011,"curvature":0,"holonomicRotation":0.0,"angularVelocity":0.0,"holonomicAngularVelocity":0.0},{"time":0.12796254951659428,"pose":{"rotation":{"radians":3.141592653589793},"translation":{"x":1.4780528155819228,"y":3.0}},"velocity":0.3838876485497831,"acceleration":3.0,"curvature":0,"holonomicRotation":0.0,"angularVelocity":0.0,"holonomicAngularVelocity":0.0},{"time":0.13167778229586988,"pose":{"rotation":{"radians":3.141592653589793},"translation":{"x":1.4766058791745653,"y":3.0}},"velocity":0.3950333468876099,"acceleration":3.0,"curvature":0,"holonomicRotation":0.0,"angularVelocity":0.0,"holonomicAngularVelocity":0.0},{"time":0.1353862857401353,"pose":{"rotation":{"radians":3.141592653589793},"translation":{"x":1.4751202671503387,"y":3.0}},"velocity":0.4061588572204061,"acceleration":2.999999999999985,"curvature":0,"holonomicRotation":0.0,"angularVelocity":0.0,"holonomicAngularVelocity":0.0},{"time":0.13908753621859218,"pose":{"rotation":{"radians":3.141592653589793},"translation":{"x":1.4735964226030658,"y":3.0}},"velocity":0.4172626086557768,"acceleration":3.000000000000015,"curvature":0,"holonomicRotation":0.0,"angularVelocity":0.0,"holonomicAngularVelocity":0.0},{"time":0.14278106334182925,"pose":{"rotation":{"radians":3.141592653589793},"translation":{"x":1.472034788626568,"y":3.0}},"velocity":0.42834319002548793,"acceleration":2.999999999999985,"curvature":0,"holonomicRotation":0.0,"angularVelocity":0.0,"holonomicAngularVelocity":0.0},{"time":0.1464664429950554,"pose":{"rotation":{"radians":3.141592653589793},"translation":{"x":1.4704358083146674,"y":3.0}},"velocity":0.43939932898516637,"acceleration":2.9999999999999925,"curvature":0,"holonomicRotation":0.0,"angularVelocity":0.0,"holonomicAngularVelocity":0.0},{"time":0.1501432914228196,"pose":{"rotation":{"radians":3.141592653589793},"translation":{"x":1.4687999247611865,"y":3.0}},"velocity":0.45042987426845893,"acceleration":2.9999999999999925,"curvature":0,"holonomicRotation":0.0,"angularVelocity":0.0,"holonomicAngularVelocity":0.0},{"time":0.15381126018632096,"pose":{"rotation":{"radians":3.141592653589793},"translation":{"x":1.467127581059947,"y":3.0}},"velocity":0.46143378055896306,"acceleration":3.0000000000000075,"curvature":0,"holonomicRotation":0.0,"angularVelocity":0.0,"holonomicAngularVelocity":0.0},{"time":0.15747003184803596,"pose":{"rotation":{"radians":3.141592653589793},"translation":{"x":1.465419220304771,"y":3.0}},"velocity":0.472410095544108,"acceleration":2.9999999999999925,"curvature":0,"holonomicRotation":0.0,"angularVelocity":0.0,"holonomicAngularVelocity":0.0},{"time":0.16111931626514664,"pose":{"rotation":{"radians":3.141592653589793},"translation":{"x":1.4636752855894806,"y":3.0}},"velocity":0.48335794879544003,"acceleration":2.9999999999999925,"curvature":0,"holonomicRotation":0.0,"angularVelocity":0.0,"holonomicAngularVelocity":0.0},{"time":0.16475884739462004,"pose":{"rotation":{"radians":3.141592653589793},"translation":{"x":1.4618962200078975,"y":3.0}},"velocity":0.4942765421838603,"acceleration":3.000000000000015,"curvature":0,"holonomicRotation":0.0,"angularVelocity":0.0,"holonomicAngularVelocity":0.0},{"time":0.16838838052997,"pose":{"rotation":{"radians":3.141592653589793},"translation":{"x":1.4600824666538441,"y":3.0}},"velocity":0.5051651415899102,"acceleration":3.000000000000023,"curvature":0,"holonomicRotation":0.0,"angularVelocity":0.0,"holonomicAngularVelocity":0.0},{"time":0.1720076899036023,"pose":{"rotation":{"radians":3.141592653589793},"translation":{"x":1.4582344686211424,"y":3.0}},"velocity":0.5160230697108071,"acceleration":3.0,"curvature":0,"holonomicRotation":0.0,"angularVelocity":0.0,"holonomicAngularVelocity":0.0},{"time":0.17561656659986738,"pose":{"rotation":{"radians":3.141592653589793},"translation":{"x":1.4563526690036146,"y":3.0}},"velocity":0.5268496997996024,"acceleration":3.0,"curvature":0,"holonomicRotation":0.0,"angularVelocity":0.0,"holonomicAngularVelocity":0.0},{"time":0.17921481673310544,"pose":{"rotation":{"radians":3.141592653589793},"translation":{"x":1.4544375108950822,"y":3.0}},"velocity":0.5376444501993166,"acceleration":3.0000000000000155,"curvature":0,"holonomicRotation":0.0,"angularVelocity":0.0,"holonomicAngularVelocity":0.0},{"time":0.18280225985243378,"pose":{"rotation":{"radians":3.141592653589793},"translation":{"x":1.452489437389368,"y":3.0}},"velocity":0.5484067795573018,"acceleration":3.000000000000031,"curvature":0,"holonomicRotation":0.0,"angularVelocity":0.0,"holonomicAngularVelocity":0.0},{"time":0.18637872754119014,"pose":{"rotation":{"radians":3.141592653589793},"translation":{"x":1.4505088915802933,"y":3.0}},"velocity":0.5591361826235708,"acceleration":2.9999999999999845,"curvature":0,"holonomicRotation":0.0,"angularVelocity":0.0,"holonomicAngularVelocity":0.0},{"time":0.18994406218397109,"pose":{"rotation":{"radians":3.141592653589793},"translation":{"x":1.4484963165616807,"y":3.0}},"velocity":0.5698321865519136,"acceleration":2.999999999999992,"curvature":0,"holonomicRotation":0.0,"angularVelocity":0.0,"holonomicAngularVelocity":0.0},{"time":0.1934981158784259,"pose":{"rotation":{"radians":3.141592653589793},"translation":{"x":1.446452155427352,"y":3.0}},"velocity":0.5804943476352781,"acceleration":3.0,"curvature":0,"holonomicRotation":0.0,"angularVelocity":0.0,"holonomicAngularVelocity":0.0},{"time":0.1970407494724108,"pose":{"rotation":{"radians":3.141592653589793},"translation":{"x":1.444376851271129,"y":3.0}},"velocity":0.5911222484172327,"acceleration":3.0,"curvature":0,"holonomicRotation":0.0,"angularVelocity":0.0,"holonomicAngularVelocity":0.0},{"time":0.20057183171002,"pose":{"rotation":{"radians":3.141592653589793},"translation":{"x":1.4422708471868342,"y":3.0}},"velocity":0.6017154951300603,"acceleration":2.999999999999992,"curvature":0,"holonomicRotation":0.0,"angularVelocity":0.0,"holonomicAngularVelocity":0.0},{"time":0.20409123847242766,"pose":{"rotation":{"radians":3.141592653589793},"translation":{"x":1.440134586268289,"y":3.0}},"velocity":0.6122737154172833,"acceleration":2.999999999999992,"curvature":0,"holonomicRotation":0.0,"angularVelocity":0.0,"holonomicAngularVelocity":0.0},{"time":0.20759885210149354,"pose":{"rotation":{"radians":3.141592653589793},"translation":{"x":1.4379685116093164,"y":3.0}},"velocity":0.6227965563044808,"acceleration":2.999999999999984,"curvature":0,"holonomicRotation":0.0,"angularVelocity":0.0,"holonomicAngularVelocity":0.0},{"time":0.21109456079581218,"pose":{"rotation":{"radians":3.141592653589793},"translation":{"x":1.4357730663037378,"y":3.0}},"velocity":0.6332836823874367,"acceleration":2.999999999999984,"curvature":0,"holonomicRotation":0.0,"angularVelocity":0.0,"holonomicAngularVelocity":0.0},{"time":0.21457825807030198,"pose":{"rotation":{"radians":3.141592653589793},"translation":{"x":1.4335486934453754,"y":3.0}},"velocity":0.6437347742109061,"acceleration":2.999999999999992,"curvature":0,"holonomicRotation":0.0,"angularVelocity":0.0,"holonomicAngularVelocity":0.0},{"time":0.21804984227167243,"pose":{"rotation":{"radians":3.141592653589793},"translation":{"x":1.4312958361280512,"y":3.0}},"velocity":0.6541495268150175,"acceleration":3.000000000000016,"curvature":0,"holonomicRotation":0.0,"angularVelocity":0.0,"holonomicAngularVelocity":0.0},{"time":0.2215092161431301,"pose":{"rotation":{"radians":3.141592653589793},"translation":{"x":1.4290149374455872,"y":3.0}},"velocity":0.6645276484293905,"acceleration":3.0,"curvature":0,"holonomicRotation":0.0,"angularVelocity":0.0,"holonomicAngularVelocity":0.0},{"time":0.2249562864325686,"pose":{"rotation":{"radians":3.141592653589793},"translation":{"x":1.4267064404918053,"y":3.0}},"velocity":0.674868859297706,"acceleration":3.000000000000008,"curvature":0,"holonomicRotation":0.0,"angularVelocity":0.0,"holonomicAngularVelocity":0.0},{"time":0.22839096353924218,"pose":{"rotation":{"radians":3.141592653589793},"translation":{"x":1.4243707883605279,"y":3.0}},"velocity":0.6851728906177267,"acceleration":2.9999999999999756,"curvature":0,"holonomicRotation":0.0,"angularVelocity":0.0,"holonomicAngularVelocity":0.0},{"time":0.23181316119456524,"pose":{"rotation":{"radians":3.141592653589793},"translation":{"x":1.4220084241455768,"y":3.0}},"velocity":0.6954394835836959,"acceleration":3.000000000000008,"curvature":0,"holonomicRotation":0.0,"angularVelocity":0.0,"holonomicAngularVelocity":0.0},{"time":0.23522279617322933,"pose":{"rotation":{"radians":3.141592653589793},"translation":{"x":1.4196197909407742,"y":3.0}},"velocity":0.7056683885196882,"acceleration":3.0,"curvature":0,"holonomicRotation":0.0,"angularVelocity":0.0,"holonomicAngularVelocity":0.0},{"time":0.2386197880313104,"pose":{"rotation":{"radians":3.141592653589793},"translation":{"x":1.4172053318399418,"y":3.0}},"velocity":0.7158593640939314,"acceleration":3.0,"curvature":0,"holonomicRotation":0.0,"angularVelocity":0.0,"holonomicAngularVelocity":0.0},{"time":0.24200405886844245,"pose":{"rotation":{"radians":3.141592653589793},"translation":{"x":1.4147654899369022,"y":3.0}},"velocity":0.7260121766053275,"acceleration":2.9999999999999836,"curvature":0,"holonomicRotation":0.0,"angularVelocity":0.0,"holonomicAngularVelocity":0.0},{"time":0.24537553311149557,"pose":{"rotation":{"radians":3.141592653589793},"translation":{"x":1.412300708325477,"y":3.0}},"velocity":0.7361265993344869,"acceleration":3.0000000000000164,"curvature":0,"holonomicRotation":0.0,"angularVelocity":0.0,"holonomicAngularVelocity":0.0},{"time":0.24873413731749092,"pose":{"rotation":{"radians":3.141592653589793},"translation":{"x":1.4098114300994884,"y":3.0}},"velocity":0.7462024119524729,"acceleration":3.0000000000000084,"curvature":0,"holonomicRotation":0.0,"angularVelocity":0.0,"holonomicAngularVelocity":0.0},{"time":0.2520797999937645,"pose":{"rotation":{"radians":3.141592653589793},"translation":{"x":1.4072980983527585,"y":3.0}},"velocity":0.7562393999812937,"acceleration":3.0000000000000084,"curvature":0,"holonomicRotation":0.0,"angularVelocity":0.0,"holonomicAngularVelocity":0.0},{"time":0.2554124514336163,"pose":{"rotation":{"radians":3.141592653589793},"translation":{"x":1.404761156179109,"y":3.0}},"velocity":0.7662373543008492,"acceleration":3.000000000000017,"curvature":0,"holonomicRotation":0.0,"angularVelocity":0.0,"holonomicAngularVelocity":0.0},{"time":0.2587320235658776,"pose":{"rotation":{"radians":3.141592653589793},"translation":{"x":1.4022010466723622,"y":3.0}},"velocity":0.7761960706976332,"acceleration":3.0000000000000333,"curvature":0,"holonomicRotation":0.0,"angularVelocity":0.0,"holonomicAngularVelocity":0.0},{"time":0.2620384498170229,"pose":{"rotation":{"radians":3.141592653589793},"translation":{"x":1.3996182129263404,"y":3.0}},"velocity":0.786115349451069,"acceleration":2.9999999999999662,"curvature":0,"holonomicRotation":0.0,"angularVelocity":0.0,"holonomicAngularVelocity":0.0},{"time":0.2653316649845847,"pose":{"rotation":{"radians":3.141592653589793},"translation":{"x":1.3970130980348652,"y":3.0}},"velocity":0.7959949949537544,"acceleration":2.999999999999983,"curvature":0,"holonomicRotation":0.0,"angularVelocity":0.0,"holonomicAngularVelocity":0.0},{"time":0.26861160512078164,"pose":{"rotation":{"radians":3.141592653589793},"translation":{"x":1.394386145091759,"y":3.0}},"velocity":0.805834815362345,"acceleration":2.9999999999999662,"curvature":0,"holonomicRotation":0.0,"angularVelocity":0.0,"holonomicAngularVelocity":0.0},{"time":0.2718782074253831,"pose":{"rotation":{"radians":3.141592653589793},"translation":{"x":1.3917377971908436,"y":3.0}},"velocity":0.8156346222761495,"acceleration":3.000000000000017,"curvature":0,"holonomicRotation":0.0,"angularVelocity":0.0,"holonomicAngularVelocity":0.0},{"time":0.2751314101469359,"pose":{"rotation":{"radians":3.141592653589793},"translation":{"x":1.3890684974259409,"y":3.0}},"velocity":0.8253942304408077,"acceleration":2.999999999999983,"curvature":0,"holonomicRotation":0.0,"angularVelocity":0.0,"holonomicAngularVelocity":0.0},{"time":0.27837115249157274,"pose":{"rotation":{"radians":3.141592653589793},"translation":{"x":1.3863786888908733,"y":3.0}},"velocity":0.8351134574747183,"acceleration":3.0,"curvature":0,"holonomicRotation":0.0,"angularVelocity":0.0,"holonomicAngularVelocity":0.0},{"time":0.2815973745387083,"pose":{"rotation":{"radians":3.141592653589793},"translation":{"x":1.3836688146794627,"y":3.0}},"velocity":0.844792123616125,"acceleration":2.9999999999999827,"curvature":0,"holonomicRotation":0.0,"angularVelocity":0.0,"holonomicAngularVelocity":0.0},{"time":0.28481001716298754,"pose":{"rotation":{"radians":3.141592653589793},"translation":{"x":1.3809393178855311,"y":3.0}},"velocity":0.8544300514889627,"acceleration":3.0,"curvature":0,"holonomicRotation":0.0,"angularVelocity":0.0,"holonomicAngularVelocity":0.0},{"time":0.2880090219619314,"pose":{"rotation":{"radians":3.141592653589793},"translation":{"x":1.3781906416029006,"y":3.0}},"velocity":0.8640270658857943,"acceleration":3.0,"curvature":0,"holonomicRotation":0.0,"angularVelocity":0.0,"holonomicAngularVelocity":0.0},{"time":0.2911943311887669,"pose":{"rotation":{"radians":3.141592653589793},"translation":{"x":1.3754232289253931,"y":3.0}},"velocity":0.8735829935663008,"acceleration":2.9999999999999827,"curvature":0,"holonomicRotation":0.0,"angularVelocity":0.0,"holonomicAngularVelocity":0.0},{"time":0.29436588768998806,"pose":{"rotation":{"radians":3.141592653589793},"translation":{"x":1.372637522946831,"y":3.0}},"velocity":0.8830976630699642,"acceleration":3.0,"curvature":0,"holonomicRotation":0.0,"angularVelocity":0.0,"holonomicAngularVelocity":0.0},{"time":0.29752363484723593,"pose":{"rotation":{"radians":3.141592653589793},"translation":{"x":1.369833966761036,"y":3.0}},"velocity":0.8925709045417078,"acceleration":3.0000000000000178,"curvature":0,"holonomicRotation":0.0,"angularVelocity":0.0,"holonomicAngularVelocity":0.0},{"time":0.30066751652312235,"pose":{"rotation":{"radians":3.141592653589793},"translation":{"x":1.36701300346183,"y":3.0}},"velocity":0.9020025495693671,"acceleration":3.0,"curvature":0,"holonomicRotation":0.0,"angularVelocity":0.0,"holonomicAngularVelocity":0.0},{"time":0.30379747701066434,"pose":{"rotation":{"radians":3.141592653589793},"translation":{"x":1.3641750761430353,"y":3.0}},"velocity":0.9113924310319931,"acceleration":3.0,"curvature":0,"holonomicRotation":0.0,"angularVelocity":0.0,"holonomicAngularVelocity":0.0},{"time":0.3069134609860233,"pose":{"rotation":{"radians":3.141592653589793},"translation":{"x":1.3613206278984742,"y":3.0}},"velocity":0.9207403829580699,"acceleration":3.0,"curvature":0,"holonomicRotation":0.0,"angularVelocity":0.0,"holonomicAngularVelocity":0.0},{"time":0.31001541346427164,"pose":{"rotation":{"radians":3.141592653589793},"translation":{"x":1.3584501018219681,"y":3.0}},"velocity":0.9300462403928149,"acceleration":2.9999999999999822,"curvature":0,"holonomicRotation":0.0,"angularVelocity":0.0,"holonomicAngularVelocity":0.0},{"time":0.31310327975793456,"pose":{"rotation":{"radians":3.141592653589793},"translation":{"x":1.35556394100734,"y":3.0}},"velocity":0.9393098392738037,"acceleration":3.0000000000000178,"curvature":0,"holonomicRotation":0.0,"angularVelocity":0.0,"holonomicAngularVelocity":0.0},{"time":0.3161770054380851,"pose":{"rotation":{"radians":3.141592653589793},"translation":{"x":1.3526625885484107,"y":3.0}},"velocity":0.9485310163142554,"acceleration":3.000000000000036,"curvature":0,"holonomicRotation":0.0,"angularVelocity":0.0,"holonomicAngularVelocity":0.0},{"time":0.319236536297774,"pose":{"rotation":{"radians":3.141592653589793},"translation":{"x":1.349746487539003,"y":3.0}},"velocity":0.9577096088933222,"acceleration":3.0000000000000364,"curvature":0,"holonomicRotation":0.0,"angularVelocity":0.0,"holonomicAngularVelocity":0.0},{"time":0.3222818183176167,"pose":{"rotation":{"radians":3.141592653589793},"translation":{"x":1.346816081072939,"y":3.0}},"velocity":0.9668454549528505,"acceleration":3.000000000000018,"curvature":0,"holonomicRotation":0.0,"angularVelocity":0.0,"holonomicAngularVelocity":0.0},{"time":0.32531279763335724,"pose":{"rotation":{"radians":3.141592653589793},"translation":{"x":1.3438718122440405,"y":3.0}},"velocity":0.9759383929000721,"acceleration":3.000000000000018,"curvature":0,"holonomicRotation":0.0,"angularVelocity":0.0,"holonomicAngularVelocity":0.0},{"time":0.3283294205052533,"pose":{"rotation":{"radians":3.141592653589793},"translation":{"x":1.3409141241461298,"y":3.0}},"velocity":0.9849882615157605,"acceleration":3.000000000000037,"curvature":0,"holonomicRotation":0.0,"angularVelocity":0.0,"holonomicAngularVelocity":0.0},{"time":0.3313316332891408,"pose":{"rotation":{"radians":3.141592653589793},"translation":{"x":1.3379434598730284,"y":3.0}},"velocity":0.993994899867423,"acceleration":3.000000000000037,"curvature":0,"holonomicRotation":0.0,"angularVelocity":0.0,"holonomicAngularVelocity":0.0},{"time":0.334319382409041,"pose":{"rotation":{"radians":3.141592653589793},"translation":{"x":1.334960262518559,"y":3.0}},"velocity":1.0029581472271236,"acceleration":2.9999999999999813,"curvature":0,"holonomicRotation":0.0,"angularVelocity":0.0,"holonomicAngularVelocity":0.0},{"time":0.33729261433119656,"pose":{"rotation":{"radians":3.141592653589793},"translation":{"x":1.331964975176543,"y":3.0}},"velocity":1.0118778429935902,"acceleration":2.9999999999999813,"curvature":0,"holonomicRotation":0.0,"angularVelocity":0.0,"holonomicAngularVelocity":0.0},{"time":0.34025127553941653,"pose":{"rotation":{"radians":3.141592653589793},"translation":{"x":1.328958040940803,"y":3.0}},"velocity":1.02075382661825,"acceleration":3.0,"curvature":0,"holonomicRotation":0.0,"angularVelocity":0.0,"holonomicAngularVelocity":0.0},{"time":0.3431953125116388,"pose":{"rotation":{"radians":3.141592653589793},"translation":{"x":1.3259399029051608,"y":3.0}},"velocity":1.029585937534917,"acceleration":3.0000000000000187,"curvature":0,"holonomicRotation":0.0,"angularVelocity":0.0,"holonomicAngularVelocity":0.0},{"time":0.34612467169760697,"pose":{"rotation":{"radians":3.141592653589793},"translation":{"x":1.3229110041634387,"y":3.0}},"velocity":1.0383740150928216,"acceleration":3.0000000000000377,"curvature":0,"holonomicRotation":0.0,"angularVelocity":0.0,"holonomicAngularVelocity":0.0},{"time":0.34903929949758267,"pose":{"rotation":{"radians":3.141592653589793},"translation":{"x":1.3198717878094581,"y":3.0}},"velocity":1.0471178984927487,"acceleration":3.000000000000019,"curvature":0,"holonomicRotation":0.0,"angularVelocity":0.0,"holonomicAngularVelocity":0.0},{"time":0.35193914224200884,"pose":{"rotation":{"radians":3.141592653589793},"translation":{"x":1.3168226969370416,"y":3.0}},"velocity":1.0558174267260272,"acceleration":2.999999999999981,"curvature":0,"holonomicRotation":0.0,"angularVelocity":0.0,"holonomicAngularVelocity":0.0},{"time":0.3548241461720553,"pose":{"rotation":{"radians":3.141592653589793},"translation":{"x":1.3137641746400108,"y":3.0}},"velocity":1.0644724385161666,"acceleration":2.999999999999981,"curvature":0,"holonomicRotation":0.0,"angularVelocity":0.0,"holonomicAngularVelocity":0.0},{"time":0.3576942574209754,"pose":{"rotation":{"radians":3.141592653589793},"translation":{"x":1.3106966640121884,"y":3.0}},"velocity":1.0730827722629268,"acceleration":3.0000000000000195,"curvature":0,"holonomicRotation":0.0,"angularVelocity":0.0,"holonomicAngularVelocity":0.0},{"time":0.36054942199621487,"pose":{"rotation":{"radians":3.141592653589793},"translation":{"x":1.307620608147396,"y":3.0}},"velocity":1.0816482659886453,"acceleration":3.0,"curvature":0,"holonomicRotation":0.0,"angularVelocity":0.0,"holonomicAngularVelocity":0.0},{"time":0.3633895857622113,"pose":{"rotation":{"radians":3.141592653589793},"translation":{"x":1.3045364501394556,"y":3.0}},"velocity":1.0901687572866348,"acceleration":3.0000000000000586,"curvature":0,"holonomicRotation":0.0,"angularVelocity":0.0,"holonomicAngularVelocity":0.0},{"time":0.36621469442383453,"pose":{"rotation":{"radians":3.141592653589793},"translation":{"x":1.3014446330821892,"y":3.0}},"velocity":1.0986440832715045,"acceleration":3.000000000000039,"curvature":0,"holonomicRotation":0.0,"angularVelocity":0.0,"holonomicAngularVelocity":0.0},{"time":0.36902469351041517,"pose":{"rotation":{"radians":3.141592653589793},"translation":{"x":1.2983456000694191,"y":3.0}},"velocity":1.1070740805312465,"acceleration":3.0,"curvature":0,"holonomicRotation":0.0,"angularVelocity":0.0,"holonomicAngularVelocity":0.0},{"time":0.3718195283603194,"pose":{"rotation":{"radians":3.141592653589793},"translation":{"x":1.2952397941949674,"y":3.0}},"velocity":1.115458585080959,"acceleration":2.99999999999998,"curvature":0,"holonomicRotation":0.0,"angularVelocity":0.0,"holonomicAngularVelocity":0.0},{"time":0.3745991441060227,"pose":{"rotation":{"radians":3.141592653589793},"translation":{"x":1.2921276585526558,"y":3.0}},"velocity":1.123797432318069,"acceleration":3.00000000000004,"curvature":0,"holonomicRotation":0.0,"angularVelocity":0.0,"holonomicAngularVelocity":0.0},{"time":0.37736348565964556,"pose":{"rotation":{"radians":3.141592653589793},"translation":{"x":1.2890096362363066,"y":3.0}},"velocity":1.1320904569789376,"acceleration":2.99999999999998,"curvature":0,"holonomicRotation":0.0,"angularVelocity":0.0,"holonomicAngularVelocity":0.0},{"time":0.3801124976989147,"pose":{"rotation":{"radians":3.141592653589793},"translation":{"x":1.2858861703397417,"y":3.0}},"velocity":1.140337493096745,"acceleration":2.9999999999999596,"curvature":0,"holonomicRotation":0.0,"angularVelocity":0.0,"holonomicAngularVelocity":0.0},{"time":0.38284612465351286,"pose":{"rotation":{"radians":3.141592653589793},"translation":{"x":1.2827577039567832,"y":3.0}},"velocity":1.1485383739605393,"acceleration":2.999999999999939,"curvature":0,"holonomicRotation":0.0,"angularVelocity":0.0,"holonomicAngularVelocity":0.0},{"time":0.38556431069178737,"pose":{"rotation":{"radians":3.141592653589793},"translation":{"x":1.2796246801812532,"y":3.0}},"velocity":1.1566929320753627,"acceleration":2.9999999999999796,"curvature":0,"holonomicRotation":0.0,"angularVelocity":0.0,"holonomicAngularVelocity":0.0},{"time":0.38826699970778633,"pose":{"rotation":{"radians":3.141592653589793},"translation":{"x":1.2764875421069737,"y":3.0}},"velocity":1.1648009991233597,"acceleration":3.0000000000000204,"curvature":0,"holonomicRotation":0.0,"angularVelocity":0.0,"holonomicAngularVelocity":0.0},{"time":0.3909541353085948,"pose":{"rotation":{"radians":3.141592653589793},"translation":{"x":1.2733467328277663,"y":3.0}},"velocity":1.172862405925785,"acceleration":3.0,"curvature":0,"holonomicRotation":0.0,"angularVelocity":0.0,"holonomicAngularVelocity":0.0},{"time":0.39362566080194267,"pose":{"rotation":{"radians":3.141592653589793},"translation":{"x":1.270202695437454,"y":3.0}},"velocity":1.1808769824058285,"acceleration":2.999999999999938,"curvature":0,"holonomicRotation":0.0,"angularVelocity":0.0,"holonomicAngularVelocity":0.0},{"time":0.39628151918406435,"pose":{"rotation":{"radians":3.141592653589793},"translation":{"x":1.267055873029858,"y":3.0}},"velocity":1.1888445575521935,"acceleration":3.0,"curvature":0,"holonomicRotation":0.0,"angularVelocity":0.0,"holonomicAngularVelocity":0.0},{"time":0.39892165312778083,"pose":{"rotation":{"radians":3.141592653589793},"translation":{"x":1.2639067086988007,"y":3.0}},"velocity":1.196764959383343,"acceleration":2.999999999999979,"curvature":0,"holonomicRotation":0.0,"angularVelocity":0.0,"holonomicAngularVelocity":0.0},{"time":0.4015460049707869,"pose":{"rotation":{"radians":3.141592653589793},"translation":{"x":1.2607556455381042,"y":3.0}},"velocity":1.204638014912361,"acceleration":2.9999999999999365,"curvature":0,"holonomicRotation":0.0,"angularVelocity":0.0,"holonomicAngularVelocity":0.0},{"time":0.40415451670412117,"pose":{"rotation":{"radians":3.141592653589793},"translation":{"x":1.2576031266415904,"y":3.0}},"velocity":1.2124635501123637,"acceleration":2.9999999999999787,"curvature":0,"holonomicRotation":0.0,"angularVelocity":0.0,"holonomicAngularVelocity":0.0},{"time":0.4067471299607999,"pose":{"rotation":{"radians":3.141592653589793},"translation":{"x":1.2544495951030812,"y":3.0}},"velocity":1.2202413898824,"acceleration":3.0000000000000213,"curvature":0,"holonomicRotation":0.0,"angularVelocity":0.0,"holonomicAngularVelocity":0.0},{"time":0.40932378600459585,"pose":{"rotation":{"radians":3.141592653589793},"translation":{"x":1.2512954940163987,"y":3.0}},"velocity":1.2279713580137879,"acceleration":3.0000000000000218,"curvature":0,"holonomicRotation":0.0,"angularVelocity":0.0,"holonomicAngularVelocity":0.0},{"time":0.411898498584702,"pose":{"rotation":{"radians":3.141592653589793},"translation":{"x":1.2481412664753653,"y":3.0}},"velocity":1.2221875959641975,"acceleration":-2.2463719229398134,"curvature":0,"holonomicRotation":0.0,"angularVelocity":0.0,"holonomicAngularVelocity":0.0},{"time":0.4144872693372643,"pose":{"rotation":{"radians":3.141592653589793},"translation":{"x":1.2449873555738027,"y":3.0}},"velocity":1.2144212837065105,"acceleration":-3.0000000000000213,"curvature":0,"holonomicRotation":0.0,"angularVelocity":0.0,"holonomicAngularVelocity":0.0},{"time":0.41709207272115906,"pose":{"rotation":{"radians":3.141592653589793},"translation":{"x":1.2418342044055333,"y":3.0}},"velocity":1.206606873554826,"acceleration":-3.000000000000064,"curvature":0,"holonomicRotation":0.0,"angularVelocity":0.0,"holonomicAngularVelocity":0.0},{"time":0.4197128526467416,"pose":{"rotation":{"radians":3.141592653589793},"translation":{"x":1.2386822560643784,"y":3.0}},"velocity":1.1987445337780787,"acceleration":-2.999999999999958,"curvature":0,"holonomicRotation":0.0,"angularVelocity":0.0,"holonomicAngularVelocity":0.0},{"time":0.4223495534766973,"pose":{"rotation":{"radians":3.141592653589793},"translation":{"x":1.235531953644161,"y":3.0}},"velocity":1.1908344312882115,"acceleration":-3.0,"curvature":0,"holonomicRotation":0.0,"angularVelocity":0.0,"holonomicAngularVelocity":0.0},{"time":0.42500212001857174,"pose":{"rotation":{"radians":3.141592653589793},"translation":{"x":1.2323837402387023,"y":3.0}},"velocity":1.182876731662588,"acceleration":-3.000000000000021,"curvature":0,"holonomicRotation":0.0,"angularVelocity":0.0,"holonomicAngularVelocity":0.0},{"time":0.4276704975173455,"pose":{"rotation":{"radians":3.141592653589793},"translation":{"x":1.2292380589418248,"y":3.0}},"velocity":1.1748715991662668,"acceleration":-3.000000000000021,"curvature":0,"holonomicRotation":0.0,"angularVelocity":0.0,"holonomicAngularVelocity":0.0},{"time":0.43035463164805365,"pose":{"rotation":{"radians":3.141592653589793},"translation":{"x":1.2260953528473504,"y":3.0}},"velocity":1.1668191967741424,"acceleration":-2.999999999999979,"curvature":0,"holonomicRotation":0.0,"angularVelocity":0.0,"holonomicAngularVelocity":0.0},{"time":0.4330544685084409,"pose":{"rotation":{"radians":3.141592653589793},"translation":{"x":1.2229560650491011,"y":3.0}},"velocity":1.1587196861929805,"acceleration":-3.0000000000000204,"curvature":0,"holonomicRotation":0.0,"angularVelocity":0.0,"holonomicAngularVelocity":0.0},{"time":0.43576995461164586,"pose":{"rotation":{"radians":3.141592653589793},"translation":{"x":1.2198206386408992,"y":3.0}},"velocity":1.1505732278833658,"acceleration":-2.999999999999959,"curvature":0,"holonomicRotation":0.0,"angularVelocity":0.0,"holonomicAngularVelocity":0.0},{"time":0.4385010368789077,"pose":{"rotation":{"radians":3.141592653589793},"translation":{"x":1.2166895167165666,"y":3.0}},"velocity":1.1423799810815805,"acceleration":-2.999999999999959,"curvature":0,"holonomicRotation":0.0,"angularVelocity":0.0,"holonomicAngularVelocity":0.0},{"time":0.4412476626322885,"pose":{"rotation":{"radians":3.141592653589793},"translation":{"x":1.213563142369925,"y":3.0}},"velocity":1.134140103821438,"acceleration":-3.0,"curvature":0,"holonomicRotation":0.0,"angularVelocity":0.0,"holonomicAngularVelocity":0.0},{"time":0.44400977958740123,"pose":{"rotation":{"radians":3.141592653589793},"translation":{"x":1.210441958694797,"y":3.0}},"velocity":1.1258537529561,"acceleration":-2.9999999999999596,"curvature":0,"holonomicRotation":0.0,"angularVelocity":0.0,"holonomicAngularVelocity":0.0},{"time":0.44678733584614067,"pose":{"rotation":{"radians":3.141592653589793},"translation":{"x":1.2073264087850042,"y":3.0}},"velocity":1.1175210841798815,"acceleration":-3.00000000000004,"curvature":0,"holonomicRotation":0.0,"angularVelocity":0.0,"holonomicAngularVelocity":0.0},{"time":0.44958027988940147,"pose":{"rotation":{"radians":3.141592653589793},"translation":{"x":1.2042169357343688,"y":3.0}},"velocity":1.109142252050099,"acceleration":-3.0,"curvature":0,"holonomicRotation":0.0,"angularVelocity":0.0,"holonomicAngularVelocity":0.0},{"time":0.45238856056978133,"pose":{"rotation":{"radians":3.141592653589793},"translation":{"x":1.2011139826367132,"y":3.0}},"velocity":1.1007174100089594,"acceleration":-3.0000000000000395,"curvature":0,"holonomicRotation":0.0,"angularVelocity":0.0,"holonomicAngularVelocity":0.0},{"time":0.4552121271042571,"pose":{"rotation":{"radians":3.141592653589793},"translation":{"x":1.198017992585859,"y":3.0}},"velocity":1.092246710405532,"acceleration":-3.0,"curvature":0,"holonomicRotation":0.0,"angularVelocity":0.0,"holonomicAngularVelocity":0.0},{"time":0.4580509290668225,"pose":{"rotation":{"radians":3.141592653589793},"translation":{"x":1.1949294086756281,"y":3.0}},"velocity":1.083730304517836,"acceleration":-3.0,"curvature":0,"holonomicRotation":0.0,"angularVelocity":0.0,"holonomicAngularVelocity":0.0},{"time":0.46090491638107967,"pose":{"rotation":{"radians":3.141592653589793},"translation":{"x":1.191848673999843,"y":3.0}},"velocity":1.0751683425750644,"acceleration":-2.9999999999999805,"curvature":0,"holonomicRotation":0.0,"angularVelocity":0.0,"holonomicAngularVelocity":0.0},{"time":0.4637740393127734,"pose":{"rotation":{"radians":3.141592653589793},"translation":{"x":1.1887762316523256,"y":3.0}},"velocity":1.0665609737799833,"acceleration":-3.0,"curvature":0,"holonomicRotation":0.0,"angularVelocity":0.0,"holonomicAngularVelocity":0.0},{"time":0.4666582484622538,"pose":{"rotation":{"radians":3.141592653589793},"translation":{"x":1.1857125247268976,"y":3.0}},"velocity":1.0579083463315422,"acceleration":-2.9999999999999614,"curvature":0,"holonomicRotation":0.0,"angularVelocity":0.0,"holonomicAngularVelocity":0.0},{"time":0.46955749475685665,"pose":{"rotation":{"radians":3.141592653589793},"translation":{"x":1.1826579963173816,"y":3.0}},"velocity":1.0492106074477334,"acceleration":-3.0000000000000573,"curvature":0,"holonomicRotation":0.0,"angularVelocity":0.0,"holonomicAngularVelocity":0.0},{"time":0.4724717294431897,"pose":{"rotation":{"radians":3.141592653589793},"translation":{"x":1.1796130895175994,"y":3.0}},"velocity":1.0404679033887343,"acceleration":-2.999999999999981,"curvature":0,"holonomicRotation":0.0,"angularVelocity":0.0,"holonomicAngularVelocity":0.0},{"time":0.47540090407930663,"pose":{"rotation":{"radians":3.141592653589793},"translation":{"x":1.1765782474213726,"y":3.0}},"velocity":1.0316803794803835,"acceleration":-3.000000000000019,"curvature":0,"holonomicRotation":0.0,"angularVelocity":0.0,"holonomicAngularVelocity":0.0},{"time":0.47834497052675523,"pose":{"rotation":{"radians":3.141592653589793},"translation":{"x":1.1735539131225239,"y":3.0}},"velocity":1.0228481801380378,"acceleration":-2.9999999999999623,"curvature":0,"holonomicRotation":0.0,"angularVelocity":0.0,"holonomicAngularVelocity":0.0},{"time":0.48130388094248566,"pose":{"rotation":{"radians":3.141592653589793},"translation":{"x":1.170540529714875,"y":3.0}},"velocity":1.0139714488908464,"acceleration":-3.0000000000000187,"curvature":0,"holonomicRotation":0.0,"angularVelocity":0.0,"holonomicAngularVelocity":0.0},{"time":0.48427758777059643,"pose":{"rotation":{"radians":3.141592653589793},"translation":{"x":1.1675385402922482,"y":3.0}},"velocity":1.0050503284065142,"acceleration":-2.9999999999999813,"curvature":0,"holonomicRotation":0.0,"angularVelocity":0.0,"holonomicAngularVelocity":0.0},{"time":0.48726604373390325,"pose":{"rotation":{"radians":3.141592653589793},"translation":{"x":1.1645483879484653,"y":3.0}},"velocity":0.9960849605165937,"acceleration":-3.0000000000000187,"curvature":0,"holonomicRotation":0.0,"angularVelocity":0.0,"holonomicAngularVelocity":0.0},{"time":0.4902692018253058,"pose":{"rotation":{"radians":3.141592653589793},"translation":{"x":1.1615705157773484,"y":3.0}},"velocity":0.987075486242386,"acceleration":-3.0000000000000187,"curvature":0,"holonomicRotation":0.0,"angularVelocity":0.0,"holonomicAngularVelocity":0.0},{"time":0.49328701529893526,"pose":{"rotation":{"radians":3.141592653589793},"translation":{"x":1.1586053668727192,"y":3.0}},"velocity":0.9780220458214977,"acceleration":-2.999999999999982,"curvature":0,"holonomicRotation":0.0,"angularVelocity":0.0,"holonomicAngularVelocity":0.0},{"time":0.49631943766105185,"pose":{"rotation":{"radians":3.141592653589793},"translation":{"x":1.1556533843284005,"y":3.0}},"velocity":0.9689247787351479,"acceleration":-2.999999999999982,"curvature":0,"holonomicRotation":0.0,"angularVelocity":0.0,"holonomicAngularVelocity":0.0},{"time":0.4993664226606743,"pose":{"rotation":{"radians":3.141592653589793},"translation":{"x":1.1527150112382138,"y":3.0}},"velocity":0.9597838237362805,"acceleration":-3.000000000000018,"curvature":0,"holonomicRotation":0.0,"angularVelocity":0.0,"holonomicAngularVelocity":0.0},{"time":0.5024279242799042,"pose":{"rotation":{"radians":3.141592653589793},"translation":{"x":1.1497906906959814,"y":3.0}},"velocity":0.9505993188785907,"acceleration":-3.0,"curvature":0,"holonomicRotation":0.0,"angularVelocity":0.0,"holonomicAngularVelocity":0.0},{"time":0.5055038967239203,"pose":{"rotation":{"radians":3.141592653589793},"translation":{"x":1.146880865795525,"y":3.0}},"velocity":0.9413714015465426,"acceleration":-3.0,"curvature":0,"holonomicRotation":0.0,"angularVelocity":0.0,"holonomicAngularVelocity":0.0},{"time":0.5085942944106051,"pose":{"rotation":{"radians":3.141592653589793},"translation":{"x":1.143985979630667,"y":3.0}},"velocity":0.9321002084864882,"acceleration":-2.999999999999964,"curvature":0,"holonomicRotation":0.0,"angularVelocity":0.0,"holonomicAngularVelocity":0.0},{"time":0.511699071959772,"pose":{"rotation":{"radians":3.141592653589793},"translation":{"x":1.1411064752952291,"y":3.0}},"velocity":0.9227858758389875,"acceleration":-2.999999999999964,"curvature":0,"holonomicRotation":0.0,"angularVelocity":0.0,"holonomicAngularVelocity":0.0},{"time":0.5148181841819441,"pose":{"rotation":{"radians":3.141592653589793},"translation":{"x":1.1382427958830337,"y":3.0}},"velocity":0.9134285391724711,"acceleration":-3.0000000000000355,"curvature":0,"holonomicRotation":0.0,"angularVelocity":0.0,"holonomicAngularVelocity":0.0},{"time":0.5179515860666504,"pose":{"rotation":{"radians":3.141592653589793},"translation":{"x":1.1353953844879028,"y":3.0}},"velocity":0.9040283335183523,"acceleration":-3.0000000000000355,"curvature":0,"holonomicRotation":0.0,"angularVelocity":0.0,"holonomicAngularVelocity":0.0},{"time":0.5210992327701841,"pose":{"rotation":{"radians":3.141592653589793},"translation":{"x":1.132564684203658,"y":3.0}},"velocity":0.8945853934077512,"acceleration":-2.999999999999965,"curvature":0,"holonomicRotation":0.0,"angularVelocity":0.0,"holonomicAngularVelocity":0.0},{"time":0.5242610796027716,"pose":{"rotation":{"radians":3.141592653589793},"translation":{"x":1.1297511381241219,"y":3.0}},"velocity":0.8850998529099888,"acceleration":-3.0,"curvature":0,"holonomicRotation":0.0,"angularVelocity":0.0,"holonomicAngularVelocity":0.0},{"time":0.5274370820150962,"pose":{"rotation":{"radians":3.141592653589793},"translation":{"x":1.1269551893431162,"y":3.0}},"velocity":0.875571845673015,"acceleration":-2.999999999999965,"curvature":0,"holonomicRotation":0.0,"angularVelocity":0.0,"holonomicAngularVelocity":0.0},{"time":0.5306271955841099,"pose":{"rotation":{"radians":3.141592653589793},"translation":{"x":1.1241772809544632,"y":3.0}},"velocity":0.8660015049659742,"acceleration":-2.9999999999999654,"curvature":0,"holonomicRotation":0.0,"angularVelocity":0.0,"holonomicAngularVelocity":0.0},{"time":0.5338313759980636,"pose":{"rotation":{"radians":3.141592653589793},"translation":{"x":1.1214178560519845,"y":3.0}},"velocity":0.8563889637241129,"acceleration":-3.0,"curvature":0,"holonomicRotation":0.0,"angularVelocity":0.0,"holonomicAngularVelocity":0.0},{"time":0.5370495790406764,"pose":{"rotation":{"radians":3.141592653589793},"translation":{"x":1.1186773577295028,"y":3.0}},"velocity":0.8467343545962747,"acceleration":-2.9999999999999654,"curvature":0,"holonomicRotation":0.0,"angularVelocity":0.0,"holonomicAngularVelocity":0.0},{"time":0.5402817605743623,"pose":{"rotation":{"radians":3.141592653589793},"translation":{"x":1.1159562290808394,"y":3.0}},"velocity":0.8370378099952169,"acceleration":-3.000000000000034,"curvature":0,"holonomicRotation":0.0,"angularVelocity":0.0,"holonomicAngularVelocity":0.0},{"time":0.5435278765224107,"pose":{"rotation":{"radians":3.141592653589793},"translation":{"x":1.1132549131998166,"y":3.0}},"velocity":0.8272994621510716,"acceleration":-2.999999999999966,"curvature":0,"holonomicRotation":0.0,"angularVelocity":0.0,"holonomicAngularVelocity":0.0},{"time":0.5467878828500241,"pose":{"rotation":{"radians":3.141592653589793},"translation":{"x":1.1105738531802571,"y":3.0}},"velocity":0.8175194431682317,"acceleration":-2.999999999999966,"curvature":0,"holonomicRotation":0.0,"angularVelocity":0.0,"holonomicAngularVelocity":0.0},{"time":0.5500617355440914,"pose":{"rotation":{"radians":3.141592653589793},"translation":{"x":1.1079134921159821,"y":3.0}},"velocity":0.8076978850860298,"acceleration":-2.9999999999999662,"curvature":0,"holonomicRotation":0.0,"angularVelocity":0.0,"holonomicAngularVelocity":0.0},{"time":0.5533493905915625,"pose":{"rotation":{"radians":3.141592653589793},"translation":{"x":1.105274273100814,"y":3.0}},"velocity":0.7978349199436165,"acceleration":-3.0,"curvature":0,"holonomicRotation":0.0,"angularVelocity":0.0,"holonomicAngularVelocity":0.0},{"time":0.5566508039562881,"pose":{"rotation":{"radians":3.141592653589793},"translation":{"x":1.1026566392285746,"y":3.0}},"velocity":0.7879306798494397,"acceleration":-3.000000000000067,"curvature":0,"holonomicRotation":0.0,"angularVelocity":0.0,"holonomicAngularVelocity":0.0},{"time":0.5599659315541532,"pose":{"rotation":{"radians":3.141592653589793},"translation":{"x":1.1000610335930863,"y":3.0}},"velocity":0.7779852970558443,"acceleration":-3.0,"curvature":0,"holonomicRotation":0.0,"angularVelocity":0.0,"holonomicAngularVelocity":0.0},{"time":0.563294729226332,"pose":{"rotation":{"radians":3.141592653589793},"translation":{"x":1.097487899288171,"y":3.0}},"velocity":0.7679989040393079,"acceleration":-3.0000000000000333,"curvature":0,"holonomicRotation":0.0,"angularVelocity":0.0,"holonomicAngularVelocity":0.0},{"time":0.5666371527104545,"pose":{"rotation":{"radians":3.141592653589793},"translation":{"x":1.0949376794076504,"y":3.0}},"velocity":0.7579716335869404,"acceleration":-3.0,"curvature":0,"holonomicRotation":0.0,"angularVelocity":0.0,"holonomicAngularVelocity":0.0},{"time":0.5699931576094621,"pose":{"rotation":{"radians":3.141592653589793},"translation":{"x":1.092410817045347,"y":3.0}},"velocity":0.7479036188899174,"acceleration":-3.0,"curvature":0,"holonomicRotation":0.0,"angularVelocity":0.0,"holonomicAngularVelocity":0.0},{"time":0.5733626993578983,"pose":{"rotation":{"radians":3.141592653589793},"translation":{"x":1.0899077552950827,"y":3.0}},"velocity":0.737794993644609,"acceleration":-2.999999999999967,"curvature":0,"holonomicRotation":0.0,"angularVelocity":0.0,"holonomicAngularVelocity":0.0},{"time":0.5767457331853434,"pose":{"rotation":{"radians":3.141592653589793},"translation":{"x":1.0874289372506798,"y":3.0}},"velocity":0.7276458921622738,"acceleration":-2.999999999999967,"curvature":0,"holonomicRotation":0.0,"angularVelocity":0.0,"holonomicAngularVelocity":0.0},{"time":0.580142214076679,"pose":{"rotation":{"radians":3.141592653589793},"translation":{"x":1.0849748060059596,"y":3.0}},"velocity":0.7174564494882671,"acceleration":-2.999999999999967,"curvature":0,"holonomicRotation":0.0,"angularVelocity":0.0,"holonomicAngularVelocity":0.0},{"time":0.5835520967288059,"pose":{"rotation":{"radians":3.141592653589793},"translation":{"x":1.082545804654745,"y":3.0}},"velocity":0.7072268015318863,"acceleration":-3.0,"curvature":0,"holonomicRotation":0.0,"angularVelocity":0.0,"holonomicAngularVelocity":0.0},{"time":0.5869753355034192,"pose":{"rotation":{"radians":3.141592653589793},"translation":{"x":1.0801423762908573,"y":3.0}},"velocity":0.6969570852080467,"acceleration":-2.9999999999999676,"curvature":0,"holonomicRotation":0.0,"angularVelocity":0.0,"holonomicAngularVelocity":0.0},{"time":0.5904118843753592,"pose":{"rotation":{"radians":3.141592653589793},"translation":{"x":1.0777649640081188,"y":3.0}},"velocity":0.6866474385922267,"acceleration":-3.0,"curvature":0,"holonomicRotation":0.0,"angularVelocity":0.0,"holonomicAngularVelocity":0.0},{"time":0.5938616968760188,"pose":{"rotation":{"radians":3.141592653589793},"translation":{"x":1.075414010900352,"y":3.0}},"velocity":0.676298001090248,"acceleration":-3.0,"curvature":0,"holonomicRotation":0.0,"angularVelocity":0.0,"holonomicAngularVelocity":0.0},{"time":0.5973247260312027,"pose":{"rotation":{"radians":3.141592653589793},"translation":{"x":1.0730899600613784,"y":3.0}},"velocity":0.6659089136246961,"acceleration":-3.000000000000032,"curvature":0,"holonomicRotation":0.0,"angularVelocity":0.0,"holonomicAngularVelocity":0.0},{"time":0.600800924292746,"pose":{"rotation":{"radians":3.141592653589793},"translation":{"x":1.0707932545850203,"y":3.0}},"velocity":0.655480318840066,"acceleration":-3.000000000000032,"curvature":0,"holonomicRotation":0.0,"angularVelocity":0.0,"holonomicAngularVelocity":0.0},{"time":0.6042902434631175,"pose":{"rotation":{"radians":3.141592653589793},"translation":{"x":1.0685243375650995,"y":3.0}},"velocity":0.6450123613289512,"acceleration":-3.000000000000032,"curvature":0,"holonomicRotation":0.0,"angularVelocity":0.0,"holonomicAngularVelocity":0.0},{"time":0.6077926346120984,"pose":{"rotation":{"radians":3.141592653589793},"translation":{"x":1.0662836520954384,"y":3.0}},"velocity":0.6345051878820087,"acceleration":-2.9999999999999685,"curvature":0,"holonomicRotation":0.0,"angularVelocity":0.0,"holonomicAngularVelocity":0.0},{"time":0.6113080479845153,"pose":{"rotation":{"radians":3.141592653589793},"translation":{"x":1.0640716412698585,"y":3.0}},"velocity":0.623958947764758,"acceleration":-3.0,"curvature":0,"holonomicRotation":0.0,"angularVelocity":0.0,"holonomicAngularVelocity":0.0},{"time":0.6148364328978297,"pose":{"rotation":{"radians":3.141592653589793},"translation":{"x":1.0618887481821826,"y":3.0}},"velocity":0.6133737930248149,"acceleration":-2.9999999999999685,"curvature":0,"holonomicRotation":0.0,"angularVelocity":0.0,"holonomicAngularVelocity":0.0},{"time":0.6183777376282277,"pose":{"rotation":{"radians":3.141592653589793},"translation":{"x":1.059735415926232,"y":3.0}},"velocity":0.602749878833621,"acceleration":-3.0000000000000315,"curvature":0,"holonomicRotation":0.0,"angularVelocity":0.0,"holonomicAngularVelocity":0.0},{"time":0.6219319092836118,"pose":{"rotation":{"radians":3.141592653589793},"translation":{"x":1.0576120875958293,"y":3.0}},"velocity":0.5920873638674687,"acceleration":-3.0,"curvature":0,"holonomicRotation":0.0,"angularVelocity":0.0,"holonomicAngularVelocity":0.0},{"time":0.6254988936616739,"pose":{"rotation":{"radians":3.141592653589793},"translation":{"x":1.055519206284796,"y":3.0}},"velocity":0.5813864107332823,"acceleration":-3.0,"curvature":0,"holonomicRotation":0.0,"angularVelocity":0.0,"holonomicAngularVelocity":0.0},{"time":0.6290786350909007,"pose":{"rotation":{"radians":3.141592653589793},"translation":{"x":1.0534572150869548,"y":3.0}},"velocity":0.5706471864456019,"acceleration":-3.000000000000031,"curvature":0,"holonomicRotation":0.0,"angularVelocity":0.0,"holonomicAngularVelocity":0.0},{"time":0.6326710762520336,"pose":{"rotation":{"radians":3.141592653589793},"translation":{"x":1.0514265570961272,"y":3.0}},"velocity":0.5598698629622031,"acceleration":-3.000000000000031,"curvature":0,"holonomicRotation":0.0,"angularVelocity":0.0,"holonomicAngularVelocity":0.0},{"time":0.6362761579770598,"pose":{"rotation":{"radians":3.141592653589793},"translation":{"x":1.0494276754061354,"y":3.0}},"velocity":0.5490546177871242,"acceleration":-3.0000000000000306,"curvature":0,"holonomicRotation":0.0,"angularVelocity":0.0,"holonomicAngularVelocity":0.0},{"time":0.639893819022325,"pose":{"rotation":{"radians":3.141592653589793},"translation":{"x":1.0474610131108015,"y":3.0}},"velocity":0.5382016346513285,"acceleration":-3.0000000000000306,"curvature":0,"holonomicRotation":0.0,"angularVelocity":0.0,"holonomicAngularVelocity":0.0},{"time":0.6435239958117425,"pose":{"rotation":{"radians":3.141592653589793},"translation":{"x":1.0455270133039474,"y":3.0}},"velocity":0.5273111042830761,"acceleration":-3.0,"curvature":0,"holonomicRotation":0.0,"angularVelocity":0.0,"holonomicAngularVelocity":0.0},{"time":0.6471666221453427,"pose":{"rotation":{"radians":3.141592653589793},"translation":{"x":1.0436261190793954,"y":3.0}},"velocity":0.5163832252822755,"acceleration":-2.9999999999999694,"curvature":0,"holonomicRotation":0.0,"angularVelocity":0.0,"holonomicAngularVelocity":0.0},{"time":0.6508216288675409,"pose":{"rotation":{"radians":3.141592653589793},"translation":{"x":1.0417587735309672,"y":3.0}},"velocity":0.5054182051156808,"acceleration":-3.00000000000003,"curvature":0,"holonomicRotation":0.0,"angularVelocity":0.0,"holonomicAngularVelocity":0.0},{"time":0.6544889434884111,"pose":{"rotation":{"radians":3.141592653589793},"translation":{"x":1.0399254197524852,"y":3.0}},"velocity":0.49441626125307025,"acceleration":-2.99999999999997,"curvature":0,"holonomicRotation":0.0,"angularVelocity":0.0,"holonomicAngularVelocity":0.0},{"time":0.6581684897499754,"pose":{"rotation":{"radians":3.141592653589793},"translation":{"x":1.0381265008377714,"y":3.0}},"velocity":0.4833776224683774,"acceleration":-2.999999999999985,"curvature":0,"holonomicRotation":0.0,"angularVelocity":0.0,"holonomicAngularVelocity":0.0},{"time":0.6618601871279108,"pose":{"rotation":{"radians":3.141592653589793},"translation":{"x":1.0363624598806476,"y":3.0}},"velocity":0.4723025303345711,"acceleration":-3.00000000000003,"curvature":0,"holonomicRotation":0.0,"angularVelocity":0.0,"holonomicAngularVelocity":0.0},{"time":0.6655639502571253,"pose":{"rotation":{"radians":3.141592653589793},"translation":{"x":1.0346337399749357,"y":3.0}},"velocity":0.4611912409469277,"acceleration":-2.9999999999999702,"curvature":0,"holonomicRotation":0.0,"angularVelocity":0.0,"holonomicAngularVelocity":0.0},{"time":0.6692796882672372,"pose":{"rotation":{"radians":3.141592653589793},"translation":{"x":1.0329407842144582,"y":3.0}},"velocity":0.45004402691659223,"acceleration":-3.0,"curvature":0,"holonomicRotation":0.0,"angularVelocity":0.0,"holonomicAngularVelocity":0.0},{"time":0.6730073040110004,"pose":{"rotation":{"radians":3.141592653589793},"translation":{"x":1.031284035693037,"y":3.0}},"velocity":0.4388611796853025,"acceleration":-3.0,"curvature":0,"holonomicRotation":0.0,"angularVelocity":0.0,"holonomicAngularVelocity":0.0},{"time":0.6767466931649618,"pose":{"rotation":{"radians":3.141592653589793},"translation":{"x":1.0296639375044943,"y":3.0}},"velocity":0.4276430122234181,"acceleration":-3.0000000000000298,"curvature":0,"holonomicRotation":0.0,"angularVelocity":0.0,"holonomicAngularVelocity":0.0},{"time":0.68049774317696,"pose":{"rotation":{"radians":3.141592653589793},"translation":{"x":1.0280809327426514,"y":3.0}},"velocity":0.41638986218742363,"acceleration":-3.0,"curvature":0,"holonomicRotation":0.0,"angularVelocity":0.0,"holonomicAngularVelocity":0.0},{"time":0.6842603320291374,"pose":{"rotation":{"radians":3.141592653589793},"translation":{"x":1.0265354645013312,"y":3.0}},"velocity":0.40510209563089145,"acceleration":-3.0,"curvature":0,"holonomicRotation":0.0,"angularVelocity":0.0,"holonomicAngularVelocity":0.0},{"time":0.6880343267776403,"pose":{"rotation":{"radians":3.141592653589793},"translation":{"x":1.0250279758743552,"y":3.0}},"velocity":0.3937801113853827,"acceleration":-2.9999999999999853,"curvature":0,"holonomicRotation":0.0,"angularVelocity":0.0,"holonomicAngularVelocity":0.0},{"time":0.69181958182055,"pose":{"rotation":{"radians":3.141592653589793},"translation":{"x":1.023558909955546,"y":3.0}},"velocity":0.38242434625665367,"acceleration":-2.9999999999999707,"curvature":0,"holonomicRotation":0.0,"angularVelocity":0.0,"holonomicAngularVelocity":0.0},{"time":0.6956159368332632,"pose":{"rotation":{"radians":3.141592653589793},"translation":{"x":1.0221287098387248,"y":3.0}},"velocity":0.3710352812185143,"acceleration":-2.9999999999999853,"curvature":0,"holonomicRotation":0.0,"angularVelocity":0.0,"holonomicAngularVelocity":0.0},{"time":0.6994232142945102,"pose":{"rotation":{"radians":3.141592653589793},"translation":{"x":1.0207378186177145,"y":3.0}},"velocity":0.3596134488347732,"acceleration":-3.0000000000000435,"curvature":0,"holonomicRotation":0.0,"angularVelocity":0.0,"holonomicAngularVelocity":0.0},{"time":0.7032412165053555,"pose":{"rotation":{"radians":3.141592653589793},"translation":{"x":1.0193866793863366,"y":3.0}},"velocity":0.34815944220223705,"acceleration":-3.0,"curvature":0,"holonomicRotation":0.0,"angularVelocity":0.0,"holonomicAngularVelocity":0.0},{"time":0.7070697219760103,"pose":{"rotation":{"radians":3.141592653589793},"translation":{"x":1.0180757352384135,"y":3.0}},"velocity":0.336673925790273,"acceleration":-2.999999999999971,"curvature":0,"holonomicRotation":0.0,"angularVelocity":0.0,"holonomicAngularVelocity":0.0},{"time":0.710908481018895,"pose":{"rotation":{"radians":3.141592653589793},"translation":{"x":1.0168054292677666,"y":3.0}},"velocity":0.3251576486616188,"acceleration":-2.999999999999971,"curvature":0,"holonomicRotation":0.0,"angularVelocity":0.0,"holonomicAngularVelocity":0.0},{"time":0.7147572103375853,"pose":{"rotation":{"radians":3.141592653589793},"translation":{"x":1.015576204568219,"y":3.0}},"velocity":0.3136114607055478,"acceleration":-3.000000000000029,"curvature":0,"holonomicRotation":0.0,"angularVelocity":0.0,"holonomicAngularVelocity":0.0},{"time":0.7186155863354401,"pose":{"rotation":{"radians":3.141592653589793},"translation":{"x":1.0143885042335918,"y":3.0}},"velocity":0.3020363327119835,"acceleration":-3.0,"curvature":0,"holonomicRotation":0.0,"angularVelocity":0.0,"holonomicAngularVelocity":0.0},{"time":0.7224832367777261,"pose":{"rotation":{"radians":3.141592653589793},"translation":{"x":1.0132427713577075,"y":3.0}},"velocity":0.2904333813851255,"acceleration":-3.000000000000014,"curvature":0,"holonomicRotation":0.0,"angularVelocity":0.0,"holonomicAngularVelocity":0.0},{"time":0.7263597303171104,"pose":{"rotation":{"radians":3.141592653589793},"translation":{"x":1.0121394490343878,"y":3.0}},"velocity":0.2788039007669723,"acceleration":-3.0000000000000284,"curvature":0,"holonomicRotation":0.0,"angularVelocity":0.0,"holonomicAngularVelocity":0.0},{"time":0.7302445632192671,"pose":{"rotation":{"radians":3.141592653589793},"translation":{"x":1.0110789803574551,"y":3.0}},"velocity":0.2671494020605021,"acceleration":-3.000000000000043,"curvature":0,"holonomicRotation":0.0,"angularVelocity":0.0,"holonomicAngularVelocity":0.0},{"time":0.7341371423809578,"pose":{"rotation":{"radians":3.141592653589793},"translation":{"x":1.0100618084207313,"y":3.0}},"velocity":0.25547166457543,"acceleration":-2.9999999999999716,"curvature":0,"holonomicRotation":0.0,"angularVelocity":0.0,"holonomicAngularVelocity":0.0},{"time":0.7380367633831115,"pose":{"rotation":{"radians":3.141592653589793},"translation":{"x":1.0090883763180385,"y":3.0}},"velocity":0.243772801568969,"acceleration":-2.999999999999993,"curvature":0,"holonomicRotation":0.0,"angularVelocity":0.0,"holonomicAngularVelocity":0.0},{"time":0.7419425818137632,"pose":{"rotation":{"radians":3.141592653589793},"translation":{"x":1.0081591271431987,"y":3.0}},"velocity":0.23205534627701416,"acceleration":-2.999999999999986,"curvature":0,"holonomicRotation":0.0,"angularVelocity":0.0,"holonomicAngularVelocity":0.0},{"time":0.7458535753476719,"pose":{"rotation":{"radians":3.141592653589793},"translation":{"x":1.0072745039900337,"y":3.0}},"velocity":0.2203223656752878,"acceleration":-3.000000000000007,"curvature":0,"holonomicRotation":0.0,"angularVelocity":0.0,"holonomicAngularVelocity":0.0},{"time":0.749768492949274,"pose":{"rotation":{"radians":3.141592653589793},"translation":{"x":1.006434949952366,"y":3.0}},"velocity":0.2085776128704818,"acceleration":-2.999999999999993,"curvature":0,"holonomicRotation":0.0,"angularVelocity":0.0,"holonomicAngularVelocity":0.0},{"time":0.7536857858586673,"pose":{"rotation":{"radians":3.141592653589793},"translation":{"x":1.0056409081240172,"y":3.0}},"velocity":0.19682573414230187,"acceleration":-2.9999999999999645,"curvature":0,"holonomicRotation":0.0,"angularVelocity":0.0,"holonomicAngularVelocity":0.0},{"time":0.7576035123698487,"pose":{"rotation":{"radians":3.141592653589793},"translation":{"x":1.0048928215988098,"y":3.0}},"velocity":0.1850725546087577,"acceleration":-3.0,"curvature":0,"holonomicRotation":0.0,"angularVelocity":0.0,"holonomicAngularVelocity":0.0},{"time":0.761519204211196,"pose":{"rotation":{"radians":3.141592653589793},"translation":{"x":1.0041911334705655,"y":3.0}},"velocity":0.17332547908471577,"acceleration":-2.999999999999993,"curvature":0,"holonomicRotation":0.0,"angularVelocity":0.0,"holonomicAngularVelocity":0.0},{"time":0.7654296755397976,"pose":{"rotation":{"radians":3.141592653589793},"translation":{"x":1.0035362868331064,"y":3.0}},"velocity":0.16159406509891117,"acceleration":-2.9999999999999787,"curvature":0,"holonomicRotation":0.0,"angularVelocity":0.0,"holonomicAngularVelocity":0.0},{"time":0.7693307442991201,"pose":{"rotation":{"radians":3.141592653589793},"translation":{"x":1.0029287247802545,"y":3.0}},"velocity":0.14989085882094377,"acceleration":-2.9999999999999716,"curvature":0,"holonomicRotation":0.0,"angularVelocity":0.0,"holonomicAngularVelocity":0.0},{"time":0.7732168165760908,"pose":{"rotation":{"radians":3.141592653589793},"translation":{"x":1.0023688904058319,"y":3.0}},"velocity":0.1382326419900316,"acceleration":-3.0000000000000284,"curvature":0,"holonomicRotation":0.0,"angularVelocity":0.0,"holonomicAngularVelocity":0.0},{"time":0.7770802513389128,"pose":{"rotation":{"radians":3.141592653589793},"translation":{"x":1.0018572268036607,"y":3.0}},"velocity":0.12664233770156566,"acceleration":-2.999999999999964,"curvature":0,"holonomicRotation":0.0,"angularVelocity":0.0,"holonomicAngularVelocity":0.0},{"time":0.7809103636485711,"pose":{"rotation":{"radians":3.141592653589793},"translation":{"x":1.001394177067563,"y":3.0}},"velocity":0.11515200077259048,"acceleration":-3.0000000000000324,"curvature":0,"holonomicRotation":0.0,"angularVelocity":0.0,"holonomicAngularVelocity":0.0},{"time":0.7846918164328996,"pose":{"rotation":{"radians":3.141592653589793},"translation":{"x":1.0009801842913606,"y":3.0}},"velocity":0.10380764241960488,"acceleration":-3.000000000000018,"curvature":0,"holonomicRotation":0.0,"angularVelocity":0.0,"holonomicAngularVelocity":0.0},{"time":0.7884019515154843,"pose":{"rotation":{"radians":3.141592653589793},"translation":{"x":1.0006156915688758,"y":3.0}},"velocity":0.09267723717185082,"acceleration":-3.0000000000000187,"curvature":0,"holonomicRotation":0.0,"angularVelocity":0.0,"holonomicAngularVelocity":0.0},{"time":0.7920062451237122,"pose":{"rotation":{"radians":3.141592653589793},"translation":{"x":1.0003011419939305,"y":3.0}},"velocity":0.08186435634716709,"acceleration":-3.0000000000000155,"curvature":0,"holonomicRotation":0.0,"angularVelocity":0.0,"holonomicAngularVelocity":0.0},{"time":0.7954504435567533,"pose":{"rotation":{"radians":3.141592653589793},"translation":{"x":1.000036978660347,"y":3.0}},"velocity":0.0715317610480437,"acceleration":-3.000000000000016,"curvature":0,"holonomicRotation":0.0,"angularVelocity":0.0,"holonomicAngularVelocity":0.0},{"time":0.7986470911557874,"pose":{"rotation":{"radians":3.141592653589793},"translation":{"x":0.9998236446619466,"y":3.0}},"velocity":0.06194181825094163,"acceleration":-2.9999999999999805,"curvature":0,"holonomicRotation":0.0,"angularVelocity":0.0,"holonomicAngularVelocity":0.0},{"time":0.801454273498178,"pose":{"rotation":{"radians":3.141592653589793},"translation":{"x":0.9996615830925522,"y":3.0}},"velocity":0.053520271223769816,"acceleration":-2.999999999999968,"curvature":0,"holonomicRotation":0.0,"angularVelocity":0.0,"holonomicAngularVelocity":0.0},{"time":0.8036513208927271,"pose":{"rotation":{"radians":3.141592653589793},"translation":{"x":0.9995512370459853,"y":3.0}},"velocity":0.04692912904012263,"acceleration":-2.999999999999994,"curvature":0,"holonomicRotation":0.0,"angularVelocity":0.0,"holonomicAngularVelocity":0.0},{"time":0.8049446888305634,"pose":{"rotation":{"radians":3.141592653589793},"translation":{"x":0.9994930496160681,"y":3.0}},"velocity":0.04304902522661358,"acceleration":-3.000000000000118,"curvature":0,"holonomicRotation":0.0,"angularVelocity":0.0,"holonomicAngularVelocity":0.0},{"time":0.8050750333378204,"pose":{"rotation":{"radians":3.141592653589793},"translation":{"x":0.9994874638966229,"y":3.0}},"velocity":0.04265799170484249,"acceleration":-3.000000000000266,"curvature":0,"holonomicRotation":0.0,"angularVelocity":2708.614345149494,"holonomicAngularVelocity":0.0},{"time":0.8062348856657148,"pose":{"rotation":{"radians":0.0},"translation":{"x":0.9995349229814713,"y":3.0}},"velocity":0.039178434721159325,"acceleration":-2.9999999999999822,"curvature":0,"holonomicRotation":0.0,"angularVelocity":0.0,"holonomicAngularVelocity":0.0},{"time":0.8091330655998701,"pose":{"rotation":{"radians":0.0},"translation":{"x":0.9996358699644357,"y":3.0}},"velocity":0.03048389491869337,"acceleration":-3.0000000000000098,"curvature":0,"holonomicRotation":0.0,"angularVelocity":0.0,"holonomicAngularVelocity":0.0},{"time":0.8192943639061012,"pose":{"rotation":{"radians":0.0},"translation":{"x":0.999790747939338,"y":3.0}},"velocity":0,"acceleration":-2.999999999999996,"curvature":0,"holonomicRotation":0.0,"angularVelocity":0.0,"holonomicAngularVelocity":0.0}]